compressor/__init__.py
compressor/base.py
compressor/cache.py
compressor/conf.py
compressor/css.py
compressor/exceptions.py
compressor/finders.py
compressor/js.py
compressor/models.py
compressor/signals.py
compressor/storage.py
compressor/test_settings.py
compressor/contrib/__init__.py
compressor/contrib/jinja2ext.py
compressor/contrib/sekizai.py
compressor/filters/__init__.py
compressor/filters/base.py
compressor/filters/cleancss.py
compressor/filters/closure.py
compressor/filters/css_default.py
compressor/filters/datauri.py
compressor/filters/template.py
compressor/filters/yuglify.py
compressor/filters/yui.py
compressor/filters/cssmin/__init__.py
compressor/filters/jsmin/__init__.py
compressor/management/__init__.py
compressor/management/commands/__init__.py
compressor/management/commands/compress.py
compressor/management/commands/mtime_cache.py
compressor/offline/__init__.py
compressor/offline/django.py
compressor/offline/jinja2.py
compressor/parser/__init__.py
compressor/parser/base.py
compressor/parser/beautifulsoup.py
compressor/parser/default_htmlparser.py
compressor/parser/html5lib.py
compressor/parser/lxml.py
compressor/templates/compressor/css_file.html
compressor/templates/compressor/css_inline.html
compressor/templates/compressor/css_preload.html
compressor/templates/compressor/js_file.html
compressor/templates/compressor/js_inline.html
compressor/templates/compressor/js_preload.html
compressor/templatetags/__init__.py
compressor/templatetags/compress.py
compressor/tests/__init__.py
compressor/tests/precompiler.py
compressor/tests/test_base.py
compressor/tests/test_conf.py
compressor/tests/test_filters.py
compressor/tests/test_finder.py
compressor/tests/test_jinja2ext.py
compressor/tests/test_mtime_cache.py
compressor/tests/test_offline.py
compressor/tests/test_parsers.py
compressor/tests/test_sekizai.py
compressor/tests/test_signals.py
compressor/tests/test_storages.py
compressor/tests/test_templatetags.py
compressor/tests/test_utils.py
django_compressor-4.5.1.dist-info/AUTHORS
django_compressor-4.5.1.dist-info/LICENSE
django_compressor-4.5.1.dist-info/METADATA
django_compressor-4.5.1.dist-info/WHEEL
django_compressor-4.5.1.dist-info/top_level.txt
django_compressor-4.5.1.dist-info/RECORD
