Metadata-Version: 2.1
Name: django_compressor
Version: 4.5.1
Summary: ('Compresses linked and inline JavaScript or CSS into single cached files.',)
Home-page: https://django-compressor.readthedocs.io/en/latest/
Maintainer: Mathieu Pillard
License: MIT
Project-URL: Source, https://github.com/django-compressor/django-compressor
Platform: UNKNOWN
Classifier: Development Status :: 5 - Production/Stable
Classifier: Framework :: Django
Classifier: Framework :: Django :: 4.2
Classifier: Framework :: Django :: 5.0
Classifier: Framework :: Django :: 5.1
Classifier: Intended Audience :: Developers
Classifier: License :: OSI Approved :: MIT License
Classifier: Operating System :: OS Independent
Classifier: Programming Language :: Python
Classifier: Programming Language :: Python :: 3 :: Only
Classifier: Programming Language :: Python :: 3.10
Classifier: Programming Language :: Python :: 3.11
Classifier: Programming Language :: Python :: 3.12
Classifier: Topic :: Internet :: WWW/HTTP
Requires-Python: >=3.8
License-File: LICENSE
License-File: AUTHORS
